pd_cli/__init__.py
pd_cli/cli.py
pdcli_inf-1.1.2.dist-info/METADATA
pdcli_inf-1.1.2.dist-info/WHEEL
pdcli_inf-1.1.2.dist-info/entry_points.txt
pdcli_inf-1.1.2.dist-info/top_level.txt
pdcli_inf-1.1.2.dist-info/RECORD
