Metadata-Version: 2.4
Name: pdcli-inf
Version: 1.1.2
Requires-Dist: click
Requires-Dist: rich
Requires-Dist: boto3
Requires-Dist: questionary
Requires-Dist: configparser
Dynamic: requires-dist
